{"frames":[{"spriteSourceSize":{"h":87,"w":82,"x":6,"y":12},"frame":{"h":71,"w":69,"x":0,"y":0}},{"spriteSourceSize":{"h":87,"w":82,"x":3,"y":11},"frame":{"h":71,"w":76,"x":70,"y":0}},{"spriteSourceSize":{"h":87,"w":82,"x":2,"y":9},"frame":{"h":72,"w":78,"x":147,"y":0}},{"spriteSourceSize":{"h":87,"w":82,"x":1,"y":8},"frame":{"h":71,"w":78,"x":226,"y":0}},{"spriteSourceSize":{"h":87,"w":82,"x":1,"y":8},"frame":{"h":70,"w":78,"x":305,"y":0}},{"spriteSourceSize":{"h":87,"w":82,"x":1,"y":9},"frame":{"h":67,"w":78,"x":384,"y":0}},{"spriteSourceSize":{"h":87,"w":82,"x":2,"y":10},"frame":{"h":66,"w":77,"x":0,"y":73}},{"spriteSourceSize":{"h":87,"w":82,"x":1,"y":12},"frame":{"h":67,"w":77,"x":78,"y":73}},{"spriteSourceSize":{"h":87,"w":82,"x":2,"y":14},"frame":{"h":66,"w":76,"x":156,"y":73}},{"spriteSourceSize":{"h":87,"w":82,"x":0,"y":22},"frame":{"h":58,"w":80,"x":233,"y":73}},{"spriteSourceSize":{"h":87,"w":82,"x":0,"y":25},"frame":{"h":55,"w":82,"x":314,"y":73}},{"spriteSourceSize":{"h":87,"w":82,"x":0,"y":25},"frame":{"h":55,"w":82,"x":314,"y":73}},{"spriteSourceSize":{"h":87,"w":82,"x":5,"y":12},"frame":{"h":70,"w":70,"x":397,"y":73}},{"spriteSourceSize":{"h":87,"w":82,"x":6,"y":8},"frame":{"h":74,"w":69,"x":0,"y":144}},{"spriteSourceSize":{"h":87,"w":82,"x":6,"y":11},"frame":{"h":73,"w":68,"x":70,"y":144}},{"spriteSourceSize":{"h":87,"w":82,"x":3,"y":11},"frame":{"h":74,"w":76,"x":139,"y":144}},{"spriteSourceSize":{"h":87,"w":82,"x":3,"y":11},"frame":{"h":74,"w":76,"x":216,"y":144}},{"spriteSourceSize":{"h":87,"w":82,"x":1,"y":10},"frame":{"h":74,"w":80,"x":293,"y":144}},{"spriteSourceSize":{"h":87,"w":82,"x":2,"y":11},"frame":{"h":72,"w":78,"x":374,"y":144}},{"spriteSourceSize":{"h":87,"w":82,"x":4,"y":8},"frame":{"h":75,"w":75,"x":0,"y":219}},{"spriteSourceSize":{"h":87,"w":82,"x":7,"y":8},"frame":{"h":74,"w":70,"x":76,"y":219}},{"spriteSourceSize":{"h":87,"w":82,"x":9,"y":9},"frame":{"h":73,"w":67,"x":147,"y":219}},{"spriteSourceSize":{"h":87,"w":82,"x":7,"y":10},"frame":{"h":72,"w":67,"x":215,"y":219}},{"spriteSourceSize":{"h":87,"w":82,"x":7,"y":12},"frame":{"h":69,"w":68,"x":283,"y":219}},{"spriteSourceSize":{"h":87,"w":82,"x":4,"y":16},"frame":{"h":65,"w":74,"x":352,"y":219}},{"spriteSourceSize":{"h":87,"w":82,"x":4,"y":16},"frame":{"h":65,"w":74,"x":352,"y":219}},{"spriteSourceSize":{"h":87,"w":82,"x":6,"y":8},"frame":{"h":76,"w":70,"x":427,"y":219}},{"spriteSourceSize":{"h":87,"w":82,"x":8,"y":5},"frame":{"h":79,"w":66,"x":0,"y":296}},{"spriteSourceSize":{"h":87,"w":82,"x":9,"y":11},"frame":{"h":71,"w":65,"x":67,"y":296}},{"spriteSourceSize":{"h":87,"w":82,"x":6,"y":11},"frame":{"h":72,"w":68,"x":133,"y":296}},{"spriteSourceSize":{"h":87,"w":82,"x":5,"y":10},"frame":{"h":73,"w":69,"x":202,"y":296}},{"spriteSourceSize":{"h":87,"w":82,"x":4,"y":10},"frame":{"h":73,"w":68,"x":272,"y":296}},{"spriteSourceSize":{"h":87,"w":82,"x":6,"y":9},"frame":{"h":74,"w":69,"x":341,"y":296}},{"spriteSourceSize":{"h":87,"w":82,"x":8,"y":10},"frame":{"h":73,"w":72,"x":411,"y":296}},{"spriteSourceSize":{"h":87,"w":82,"x":8,"y":9},"frame":{"h":76,"w":73,"x":0,"y":376}},{"spriteSourceSize":{"h":87,"w":82,"x":8,"y":9},"frame":{"h":76,"w":73,"x":0,"y":376}},{"spriteSourceSize":{"h":87,"w":82,"x":6,"y":10},"frame":{"h":74,"w":70,"x":74,"y":376}},{"spriteSourceSize":{"h":87,"w":82,"x":4,"y":11},"frame":{"h":72,"w":69,"x":145,"y":376}},{"spriteSourceSize":{"h":87,"w":82,"x":4,"y":11},"frame":{"h":71,"w":70,"x":215,"y":376}},{"spriteSourceSize":{"h":87,"w":82,"x":9,"y":11},"frame":{"h":71,"w":65,"x":286,"y":376}},{"spriteSourceSize":{"h":87,"w":82,"x":9,"y":11},"frame":{"h":72,"w":68,"x":352,"y":376}},{"spriteSourceSize":{"h":87,"w":82,"x":9,"y":10},"frame":{"h":73,"w":69,"x":421,"y":376}},{"spriteSourceSize":{"h":87,"w":82,"x":11,"y":10},"frame":{"h":73,"w":67,"x":0,"y":453}},{"spriteSourceSize":{"h":87,"w":82,"x":8,"y":9},"frame":{"h":74,"w":69,"x":68,"y":453}},{"spriteSourceSize":{"h":87,"w":82,"x":3,"y":10},"frame":{"h":73,"w":72,"x":138,"y":453}},{"spriteSourceSize":{"h":87,"w":82,"x":2,"y":9},"frame":{"h":76,"w":73,"x":211,"y":453}},{"spriteSourceSize":{"h":87,"w":82,"x":2,"y":9},"frame":{"h":76,"w":73,"x":211,"y":453}},{"spriteSourceSize":{"h":87,"w":82,"x":7,"y":10},"frame":{"h":74,"w":70,"x":285,"y":453}},{"spriteSourceSize":{"h":87,"w":82,"x":10,"y":11},"frame":{"h":72,"w":69,"x":356,"y":453}},{"spriteSourceSize":{"h":87,"w":82,"x":9,"y":11},"frame":{"h":71,"w":70,"x":426,"y":453}},{"spriteSourceSize":{"h":87,"w":82,"x":9,"y":10},"frame":{"h":75,"w":59,"x":0,"y":530}},{"spriteSourceSize":{"h":87,"w":82,"x":10,"y":11},"frame":{"h":75,"w":58,"x":60,"y":530}},{"spriteSourceSize":{"h":87,"w":82,"x":8,"y":10},"frame":{"h":76,"w":60,"x":119,"y":530}},{"spriteSourceSize":{"h":87,"w":82,"x":8,"y":10},"frame":{"h":76,"w":61,"x":180,"y":530}},{"spriteSourceSize":{"h":87,"w":82,"x":8,"y":9},"frame":{"h":77,"w":63,"x":242,"y":530}},{"spriteSourceSize":{"h":87,"w":82,"x":8,"y":8},"frame":{"h":78,"w":68,"x":306,"y":530}},{"spriteSourceSize":{"h":87,"w":82,"x":8,"y":8},"frame":{"h":78,"w":68,"x":375,"y":530}},{"spriteSourceSize":{"h":87,"w":82,"x":8,"y":8},"frame":{"h":78,"w":68,"x":375,"y":530}},{"spriteSourceSize":{"h":87,"w":82,"x":10,"y":8},"frame":{"h":78,"w":63,"x":444,"y":530}},{"spriteSourceSize":{"h":87,"w":82,"x":11,"y":9},"frame":{"h":77,"w":61,"x":0,"y":609}},{"spriteSourceSize":{"h":87,"w":82,"x":10,"y":10},"frame":{"h":76,"w":58,"x":62,"y":609}},{"spriteSourceSize":{"h":87,"w":82,"x":10,"y":9},"frame":{"h":76,"w":58,"x":121,"y":609}},{"spriteSourceSize":{"h":87,"w":82,"x":8,"y":9},"frame":{"h":76,"w":61,"x":180,"y":609}},{"spriteSourceSize":{"h":87,"w":82,"x":7,"y":8},"frame":{"h":78,"w":64,"x":242,"y":609}},{"spriteSourceSize":{"h":87,"w":82,"x":6,"y":8},"frame":{"h":79,"w":67,"x":307,"y":609}},{"spriteSourceSize":{"h":87,"w":82,"x":4,"y":7},"frame":{"h":80,"w":69,"x":375,"y":609}},{"spriteSourceSize":{"h":87,"w":82,"x":3,"y":7},"frame":{"h":80,"w":73,"x":0,"y":690}},{"spriteSourceSize":{"h":87,"w":82,"x":2,"y":7},"frame":{"h":80,"w":74,"x":74,"y":690}},{"spriteSourceSize":{"h":87,"w":82,"x":2,"y":7},"frame":{"h":80,"w":74,"x":74,"y":690}},{"spriteSourceSize":{"h":87,"w":82,"x":3,"y":8},"frame":{"h":79,"w":73,"x":149,"y":690}},{"spriteSourceSize":{"h":87,"w":82,"x":4,"y":9},"frame":{"h":78,"w":70,"x":223,"y":690}},{"spriteSourceSize":{"h":87,"w":82,"x":7,"y":9},"frame":{"h":77,"w":64,"x":294,"y":690}},{"spriteSourceSize":{"h":87,"w":82,"x":8,"y":9},"frame":{"h":75,"w":66,"x":359,"y":690}},{"spriteSourceSize":{"h":87,"w":82,"x":7,"y":10},"frame":{"h":74,"w":63,"x":426,"y":690}},{"spriteSourceSize":{"h":87,"w":82,"x":10,"y":9},"frame":{"h":75,"w":61,"x":0,"y":771}},{"spriteSourceSize":{"h":87,"w":82,"x":12,"y":10},"frame":{"h":74,"w":63,"x":62,"y":771}},{"spriteSourceSize":{"h":87,"w":82,"x":12,"y":10},"frame":{"h":74,"w":63,"x":126,"y":771}},{"spriteSourceSize":{"h":87,"w":82,"x":12,"y":9},"frame":{"h":74,"w":63,"x":190,"y":771}},{"spriteSourceSize":{"h":87,"w":82,"x":13,"y":9},"frame":{"h":74,"w":58,"x":254,"y":771}},{"spriteSourceSize":{"h":87,"w":82,"x":13,"y":9},"frame":{"h":74,"w":57,"x":313,"y":771}},{"spriteSourceSize":{"h":87,"w":82,"x":7,"y":6},"frame":{"h":78,"w":64,"x":371,"y":771}},{"spriteSourceSize":{"h":87,"w":82,"x":10,"y":9},"frame":{"h":75,"w":61,"x":436,"y":771}},{"spriteSourceSize":{"h":87,"w":82,"x":13,"y":9},"frame":{"h":75,"w":56,"x":0,"y":850}},{"spriteSourceSize":{"h":87,"w":82,"x":11,"y":9},"frame":{"h":75,"w":60,"x":57,"y":850}},{"spriteSourceSize":{"h":87,"w":82,"x":10,"y":16},"frame":{"h":68,"w":64,"x":118,"y":850}},{"spriteSourceSize":{"h":87,"w":82,"x":10,"y":15},"frame":{"h":71,"w":63,"x":183,"y":850}},{"spriteSourceSize":{"h":87,"w":82,"x":10,"y":16},"frame":{"h":68,"w":64,"x":247,"y":850}},{"spriteSourceSize":{"h":87,"w":82,"x":12,"y":16},"frame":{"h":68,"w":56,"x":312,"y":850}},{"spriteSourceSize":{"h":87,"w":82,"x":7,"y":10},"frame":{"h":75,"w":61,"x":369,"y":850}},{"spriteSourceSize":{"h":87,"w":82,"x":10,"y":10},"frame":{"h":75,"w":56,"x":431,"y":850}},{"spriteSourceSize":{"h":87,"w":82,"x":19,"y":0},"frame":{"h":81,"w":44,"x":0,"y":926}},{"spriteSourceSize":{"h":87,"w":82,"x":19,"y":0},"frame":{"h":79,"w":45,"x":45,"y":926}},{"spriteSourceSize":{"h":87,"w":82,"x":13,"y":10},"frame":{"h":72,"w":54,"x":91,"y":926}},{"spriteSourceSize":{"h":87,"w":82,"x":8,"y":5},"frame":{"h":70,"w":66,"x":146,"y":926}},{"spriteSourceSize":{"h":87,"w":82,"x":19,"y":0},"frame":{"h":78,"w":45,"x":213,"y":926}},{"spriteSourceSize":{"h":87,"w":82,"x":3,"y":15},"frame":{"h":51,"w":74,"x":259,"y":926}},{"spriteSourceSize":{"h":87,"w":82,"x":19,"y":4},"frame":{"h":79,"w":44,"x":334,"y":926}},{"spriteSourceSize":{"h":87,"w":82,"x":19,"y":0},"frame":{"h":79,"w":46,"x":379,"y":926}},{"spriteSourceSize":{"h":87,"w":82,"x":19,"y":7},"frame":{"h":73,"w":44,"x":426,"y":926}},{"spriteSourceSize":{"h":87,"w":82,"x":40,"y":51},"frame":{"h":2,"w":2,"x":471,"y":926}}]}